batch_http_request-0.1.4.dist-info/METADATA
batch_http_request-0.1.4.dist-info/WHEEL
batch_http_request-0.1.4.dist-info/licenses/LICENSE
batch_http_request/__init__.py
batch_http_request/__init__.pyi
batch_http_request/py.typed
batch_http_request/batch_http_request.cpython-38-x86_64-linux-gnu.so
batch_http_request-0.1.4.dist-info/RECORD
