Metadata-Version: 2.3
Name: batch_http_request
Version: 0.1.4
Classifier: Programming Language :: Rust
Classifier: Programming Language :: Python :: Implementation :: CPython
Classifier: Programming Language :: Python :: Implementation :: PyPy
License-File: LICENSE
Summary: High performance batch http rqeuest
Requires-Python: >=3.8
Project-URL: Homepage, https://github.com/Dorbmon/batch_http
